{"cameraMode":{"drawMode":0,"name":"Shaded","section":"Shading Mode"},"sceneLighting":false,"audioPlay":false,"sceneViewState":{"m_AlwaysRefresh":false,"showFog":true,"showSkybox":false,"showFlares":true,"showImageEffects":true,"showParticleSystems":true,"showVisualEffectGraphs":true,"m_FxEnabled":true},"in2DMode":false,"pivot":{"x":-0.07035326957702637,"y":6.031777858734131,"z":0.07647132873535156},"rotation":{"x":0.011999367736279965,"y":0.007499365136027336,"z":-0.00008999912824947387,"w":0.9998992681503296},"size":2.738189220428467,"orthographic":false}